src/web_scraper/__init__.py
src/web_scraper/scraper.py
src/web_scraper/utils/__init__.py
src/web_scraper/utils/argparse.py
src/web_scraper/utils/browser.py
src/web_scraper/utils/json.py
src/web_scraper/utils/logger.py
src/web_scraper/utils/notifier.py
src/web_scraper/utils/parser.py
ajs_scraper-0.2.1.dist-info/LICENSE
ajs_scraper-0.2.1.dist-info/METADATA
ajs_scraper-0.2.1.dist-info/WHEEL
ajs_scraper-0.2.1.dist-info/entry_points.txt
ajs_scraper-0.2.1.dist-info/top_level.txt
ajs_scraper-0.2.1.dist-info/RECORD
