Metadata-Version: 2.1
Name: ajs-scraper
Version: 0.2.1
Summary: Dynamic web scraper specifically designed for AnsularJS websites that runs at specified time intervals and notifies you about specific updates on the site
Author-email: Rodrigo Martin Núñez <rodrigomartinnunez@gmail.com>
Maintainer-email: Rodrigo Martin Núñez <rodrigomartinnunez@gmail.com>
License: GNU GENERAL PUBLIC LICENSE
Project-URL: Homepage, https://github.com/P-ict0/AngularJS-Dynamic-Web-Scraper.git
Project-URL: Bug Reports, https://github.com/P-ict0/AngularJS-Dynamic-Web-Scraper/issues
Keywords: web,setuptools,development,scraper,angularjs,selenium
Classifier: Development Status :: 3 - Alpha
Classifier: Intended Audience :: Developers
Classifier: Topic :: Software Development :: Build Tools
Classifier: License :: OSI Approved :: GNU General Public License v3 (GPLv3)
Classifier: Programming Language :: Python :: 3
Classifier: Programming Language :: Python :: 3.10
Classifier: Programming Language :: Python :: 3.11
Requires-Python: >=3.10
License-File: LICENSE
Requires-Dist: beautifulsoup4 ==4.12.3
Requires-Dist: bs4 ==0.0.2
Requires-Dist: colorlog ==6.8.2
Requires-Dist: lxml ==5.2.2
Requires-Dist: path ==16.14.0
Requires-Dist: selenium ==4.21.0
Requires-Dist: win11toast ==0.35 ; platform_system == "Windows"
